pyinfinitive/__init__.py
pyinfinitive/pyinfinitive.py
pyinfinitive-0.0.5.dist-info/METADATA
pyinfinitive-0.0.5.dist-info/RECORD
pyinfinitive-0.0.5.dist-info/WHEEL
pyinfinitive-0.0.5.dist-info/top_level.txt
