Metadata-Version: 2.1
Name: pyinfinitive
Version: 0.0.5
Summary: An API wrapper for the Infinitive project.
Home-page: https://github.com/mww012/pyinfinitive.git
Author: Michael Wood
Author-email: mww012@gmail.com
License: UNKNOWN
Platform: UNKNOWN
Classifier: Programming Language :: Python :: 3
Classifier: License :: OSI Approved :: MIT License
Classifier: Operating System :: OS Independent
